nest/MessagePatternHandler.py
nest/NestMsClient.py
nest/NestMsServer.py
nest/TCPClient.py
nest/TCPServer.py
nest/__init__.py
nest/utils.py
python_nestjs-0.0.4.dist-info/LICENSE
python_nestjs-0.0.4.dist-info/METADATA
python_nestjs-0.0.4.dist-info/WHEEL
python_nestjs-0.0.4.dist-info/top_level.txt
python_nestjs-0.0.4.dist-info/RECORD
